{
    "homepage": "https://github.com/Mrs4s/go-cqhttp",
    "description": "基于 Mirai 以及 MiraiGo 的 OneBot Golang 原生实现。",
    "version": "22.10.29",
    "license": "AGPL-3.0-only",
    "url": "https://github.com/5p1ral/go-cqhttp-nightly/releases/download/22.10.29/go-cqhttp_windows_amd64.zip",
    "hash": "239e2c7eb4b32bda4600ff5c8b16dae0a09abfefd3f63ae882bfee73b830fffb",
    "bin": "go-cqhttp.exe",
    "checkver": {
        "url": "https://github.com/5p1ral/go-cqhttp-nightly/releases/latest",
        "regex": "releases/tag/([\\d.\\-a-z]+)"
    },
    "autoupdate": {
        "url": "https://github.com/5p1ral/go-cqhttp-nightly/releases/download/$version/go-cqhttp_windows_amd64.zip",
        "hash": {
            "url": "https://github.com/5p1ral/go-cqhttp-nightly/releases/download/$version/go-cqhttp_checksums.txt",
            "mode": "extract",
            "regex": "$base64 go-cqhttp_windows_amd64.zip"
        }
    }
}
